pytest_approvaltests_geo/__init__.py
pytest_approvaltests_geo/_version.py
pytest_approvaltests_geo/existing_dir_writer.py
pytest_approvaltests_geo/factories.py
pytest_approvaltests_geo/float_utils.py
pytest_approvaltests_geo/geo_io.py
pytest_approvaltests_geo/geo_options.py
pytest_approvaltests_geo/scrubbers.py
pytest_approvaltests_geo/comparators/__init__.py
pytest_approvaltests_geo/comparators/compare_geo_ncs.py
pytest_approvaltests_geo/comparators/compare_geo_tiffs.py
pytest_approvaltests_geo/comparators/compare_geo_zarrs.py
pytest_approvaltests_geo/differs/__init__.py
pytest_approvaltests_geo/differs/differ_of_geo_dataset.py
pytest_approvaltests_geo/differs/differ_of_geo_ncs.py
pytest_approvaltests_geo/differs/differ_of_geo_tiffs.py
pytest_approvaltests_geo/differs/differ_of_geo_zarrs.py
pytest_approvaltests_geo/differs/difference.py
pytest_approvaltests_geo/namer/__init__.py
pytest_approvaltests_geo/namer/stack_frame_namer_with_external_data_dir.py
pytest_approvaltests_geo/reporters/__init__.py
pytest_approvaltests_geo/reporters/report_geo_ncs.py
pytest_approvaltests_geo/reporters/report_geo_tiffs.py
pytest_approvaltests_geo/reporters/report_geo_zarrs.py
pytest_approvaltests_geo-1.9.0.dist-info/licenses/LICENSE
pytest_approvaltests_geo-1.9.0.dist-info/METADATA
pytest_approvaltests_geo-1.9.0.dist-info/WHEEL
pytest_approvaltests_geo-1.9.0.dist-info/entry_points.txt
pytest_approvaltests_geo-1.9.0.dist-info/top_level.txt
pytest_approvaltests_geo-1.9.0.dist-info/RECORD
