Metadata-Version: 2.4
Name: pytest-approvaltests-geo
Version: 1.9.0
Summary: Extension for ApprovalTests.Python specific to geo data verification
Home-page: https://github.com/TUW-GEO/ApprovalTests.Python.GeoExtensions
Author: TU Wien GEO MRS group
Author-email: remote.sensing@geo.tuwien.ac.at
Platform: any
Classifier: Development Status :: 5 - Production/Stable
Classifier: Intended Audience :: Science/Research
Classifier: License :: OSI Approved :: MIT License
Classifier: Topic :: Scientific/Engineering
Classifier: Topic :: Scientific/Engineering :: GIS
Classifier: Topic :: Software Development :: Libraries
Classifier: Programming Language :: Python :: 3
Classifier: Programming Language :: Python :: 3.7
Classifier: Programming Language :: Python :: 3.8
Classifier: Programming Language :: Python :: 3.9
Classifier: Operating System :: Microsoft :: Windows
Classifier: Operating System :: POSIX
Classifier: Natural Language :: English
License-File: LICENSE
Requires-Dist: pytest
Requires-Dist: approvaltests
Requires-Dist: rioxarray
Requires-Dist: xarray
Provides-Extra: test
Requires-Dist: zarr; extra == "test"
Requires-Dist: netcdf4; extra == "test"
Requires-Dist: pandas; extra == "test"
Requires-Dist: pytest-cov; extra == "test"
Provides-Extra: zarr
Requires-Dist: zarr; extra == "zarr"
Dynamic: license-file
